nord/__init__.py
nord/_utils.py
nord/_version.py
nord/api.py
nord/cli.py
nord/vpn.py
nord-0.2.0.dist-info/DESCRIPTION.rst
nord-0.2.0.dist-info/METADATA
nord-0.2.0.dist-info/RECORD
nord-0.2.0.dist-info/WHEEL
nord-0.2.0.dist-info/entry_points.txt
nord-0.2.0.dist-info/metadata.json
nord-0.2.0.dist-info/top_level.txt
