Metadata-Version: 2.0
Name: nord
Version: 0.2.0
Summary: Unofficial NordVPN client
Home-page: https://github.com/jbweston/nord
Author: Joseph Weston
Author-email: joseph@weston.cloud
License: GNU General Public License v3
Platform: GNU/Linux
Requires-Dist: decorator
Requires-Dist: structlog
Requires-Dist: aiohttp
Requires-Dist: termcolor
Provides-Extra: dev
Requires-Dist: pylint; extra == 'dev'
Requires-Dist: pep8; extra == 'dev'
Requires-Dist: sphinx; extra == 'dev'
Requires-Dist: sphinx-autobuild; extra == 'dev'
Requires-Dist: sphinx-rtd-theme; extra == 'dev'
